[
  {
    "line": 2,
    "elements": [
      {
        "comments": [
          {
            "line": 6,
            "value": "#This is declarative BDD, not line by line description"
          }
        ],
        "before": [
          {
            "result": {
              "duration": 117757024,
              "error_message": "java.lang.NullPointerException\n\tat java.util.Objects.requireNonNull(Objects.java:203)\n\tat org.openqa.selenium.interactions.Actions.\u003cinit\u003e(Actions.java:65)\n\tat com.amazonbdd.test.qa.testBase.TestBase.\u003cinit\u003e(TestBase.java:14)\n\tat com.amazonbdd.test.qa.stepdefinitions.ServiceHooks.initializeTest(ServiceHooks.java:24)\n\tat sun.reflect.NativeMethodAccessorImpl.invoke0(Native Method)\n\tat sun.reflect.NativeMethodAccessorImpl.invoke(NativeMethodAccessorImpl.java:62)\n\tat sun.reflect.DelegatingMethodAccessorImpl.invoke(DelegatingMethodAccessorImpl.java:43)\n\tat java.lang.reflect.Method.invoke(Method.java:498)\n\tat cucumber.runtime.Utils$1.call(Utils.java:40)\n\tat cucumber.runtime.Timeout.timeout(Timeout.java:16)\n\tat cucumber.runtime.Utils.invoke(Utils.java:34)\n\tat cucumber.runtime.java.JavaHookDefinition.execute(JavaHookDefinition.java:60)\n\tat cucumber.runtime.Runtime.runHookIfTagsMatch(Runtime.java:224)\n\tat cucumber.runtime.Runtime.runHooks(Runtime.java:212)\n\tat cucumber.runtime.Runtime.runBeforeHooks(Runtime.java:202)\n\tat cucumber.runtime.model.CucumberScenario.run(CucumberScenario.java:40)\n\tat cucumber.runtime.model.CucumberFeature.run(CucumberFeature.java:165)\n\tat cucumber.api.testng.TestNGCucumberRunner.runCucumber(TestNGCucumberRunner.java:63)\n\tat com.amazonbdd.test.qa.testRunner.TestRunner.feature(TestRunner.java:28)\n\tat sun.reflect.NativeMethodAccessorImpl.invoke0(Native Method)\n\tat sun.reflect.NativeMethodAccessorImpl.invoke(NativeMethodAccessorImpl.java:62)\n\tat sun.reflect.DelegatingMethodAccessorImpl.invoke(DelegatingMethodAccessorImpl.java:43)\n\tat java.lang.reflect.Method.invoke(Method.java:498)\n\tat org.testng.internal.MethodInvocationHelper.invokeMethod(MethodInvocationHelper.java:86)\n\tat org.testng.internal.Invoker.invokeMethod(Invoker.java:643)\n\tat org.testng.internal.Invoker.invokeTestMethod(Invoker.java:820)\n\tat org.testng.internal.Invoker.invokeTestMethods(Invoker.java:1128)\n\tat org.testng.internal.TestMethodWorker.invokeTestMethods(TestMethodWorker.java:129)\n\tat org.testng.internal.TestMethodWorker.run(TestMethodWorker.java:112)\n\tat org.testng.TestRunner.privateRun(TestRunner.java:782)\n\tat org.testng.TestRunner.run(TestRunner.java:632)\n\tat org.testng.SuiteRunner.runTest(SuiteRunner.java:366)\n\tat org.testng.SuiteRunner.runSequentially(SuiteRunner.java:361)\n\tat org.testng.SuiteRunner.privateRun(SuiteRunner.java:319)\n\tat org.testng.SuiteRunner.run(SuiteRunner.java:268)\n\tat org.testng.SuiteRunnerWorker.runSuite(SuiteRunnerWorker.java:52)\n\tat org.testng.SuiteRunnerWorker.run(SuiteRunnerWorker.java:86)\n\tat org.testng.TestNG.runSuitesSequentially(TestNG.java:1244)\n\tat org.testng.TestNG.runSuitesLocally(TestNG.java:1169)\n\tat org.testng.TestNG.run(TestNG.java:1064)\n\tat org.apache.maven.surefire.testng.TestNGExecutor.run(TestNGExecutor.java:283)\n\tat org.apache.maven.surefire.testng.TestNGXmlTestSuite.execute(TestNGXmlTestSuite.java:75)\n\tat org.apache.maven.surefire.testng.TestNGProvider.invoke(TestNGProvider.java:120)\n\tat org.apache.maven.surefire.booter.ForkedBooter.invokeProviderInSameClassLoader(ForkedBooter.java:384)\n\tat org.apache.maven.surefire.booter.ForkedBooter.runSuitesInProcess(ForkedBooter.java:345)\n\tat org.apache.maven.surefire.booter.ForkedBooter.execute(ForkedBooter.java:126)\n\tat org.apache.maven.surefire.booter.ForkedBooter.main(ForkedBooter.java:418)\n",
              "status": "failed"
            },
            "match": {
              "location": "ServiceHooks.initializeTest()"
            }
          }
        ],
        "line": 8,
        "name": "",
        "description": "",
        "id": "as-an-user;",
        "after": [
          {
            "result": {
              "duration": 11162614,
              "error_message": "java.lang.NullPointerException\n\tat com.amazonbdd.test.qa.stepdefinitions.ServiceHooks.endTest(ServiceHooks.java:34)\n\tat sun.reflect.NativeMethodAccessorImpl.invoke0(Native Method)\n\tat sun.reflect.NativeMethodAccessorImpl.invoke(NativeMethodAccessorImpl.java:62)\n\tat sun.reflect.DelegatingMethodAccessorImpl.invoke(DelegatingMethodAccessorImpl.java:43)\n\tat java.lang.reflect.Method.invoke(Method.java:498)\n\tat cucumber.runtime.Utils$1.call(Utils.java:40)\n\tat cucumber.runtime.Timeout.timeout(Timeout.java:16)\n\tat cucumber.runtime.Utils.invoke(Utils.java:34)\n\tat cucumber.runtime.java.JavaHookDefinition.execute(JavaHookDefinition.java:60)\n\tat cucumber.runtime.Runtime.runHookIfTagsMatch(Runtime.java:224)\n\tat cucumber.runtime.Runtime.runHooks(Runtime.java:212)\n\tat cucumber.runtime.Runtime.runAfterHooks(Runtime.java:206)\n\tat cucumber.runtime.model.CucumberScenario.run(CucumberScenario.java:46)\n\tat cucumber.runtime.model.CucumberFeature.run(CucumberFeature.java:165)\n\tat cucumber.api.testng.TestNGCucumberRunner.runCucumber(TestNGCucumberRunner.java:63)\n\tat com.amazonbdd.test.qa.testRunner.TestRunner.feature(TestRunner.java:28)\n\tat sun.reflect.NativeMethodAccessorImpl.invoke0(Native Method)\n\tat sun.reflect.NativeMethodAccessorImpl.invoke(NativeMethodAccessorImpl.java:62)\n\tat sun.reflect.DelegatingMethodAccessorImpl.invoke(DelegatingMethodAccessorImpl.java:43)\n\tat java.lang.reflect.Method.invoke(Method.java:498)\n\tat org.testng.internal.MethodInvocationHelper.invokeMethod(MethodInvocationHelper.java:86)\n\tat org.testng.internal.Invoker.invokeMethod(Invoker.java:643)\n\tat org.testng.internal.Invoker.invokeTestMethod(Invoker.java:820)\n\tat org.testng.internal.Invoker.invokeTestMethods(Invoker.java:1128)\n\tat org.testng.internal.TestMethodWorker.invokeTestMethods(TestMethodWorker.java:129)\n\tat org.testng.internal.TestMethodWorker.run(TestMethodWorker.java:112)\n\tat org.testng.TestRunner.privateRun(TestRunner.java:782)\n\tat org.testng.TestRunner.run(TestRunner.java:632)\n\tat org.testng.SuiteRunner.runTest(SuiteRunner.java:366)\n\tat org.testng.SuiteRunner.runSequentially(SuiteRunner.java:361)\n\tat org.testng.SuiteRunner.privateRun(SuiteRunner.java:319)\n\tat org.testng.SuiteRunner.run(SuiteRunner.java:268)\n\tat org.testng.SuiteRunnerWorker.runSuite(SuiteRunnerWorker.java:52)\n\tat org.testng.SuiteRunnerWorker.run(SuiteRunnerWorker.java:86)\n\tat org.testng.TestNG.runSuitesSequentially(TestNG.java:1244)\n\tat org.testng.TestNG.runSuitesLocally(TestNG.java:1169)\n\tat org.testng.TestNG.run(TestNG.java:1064)\n\tat org.apache.maven.surefire.testng.TestNGExecutor.run(TestNGExecutor.java:283)\n\tat org.apache.maven.surefire.testng.TestNGXmlTestSuite.execute(TestNGXmlTestSuite.java:75)\n\tat org.apache.maven.surefire.testng.TestNGProvider.invoke(TestNGProvider.java:120)\n\tat org.apache.maven.surefire.booter.ForkedBooter.invokeProviderInSameClassLoader(ForkedBooter.java:384)\n\tat org.apache.maven.surefire.booter.ForkedBooter.runSuitesInProcess(ForkedBooter.java:345)\n\tat org.apache.maven.surefire.booter.ForkedBooter.execute(ForkedBooter.java:126)\n\tat org.apache.maven.surefire.booter.ForkedBooter.main(ForkedBooter.java:418)\n",
              "status": "failed"
            },
            "match": {
              "location": "ServiceHooks.endTest(Scenario)"
            }
          }
        ],
        "type": "scenario",
        "keyword": "Scenario",
        "steps": [
          {
            "result": {
              "status": "skipped"
            },
            "line": 9,
            "name": "I am on the Amazon page URL",
            "match": {
              "location": "RegistryPageStepDefinitions.i_am_on_the_Amazon_page_URL()"
            },
            "keyword": "Given "
          },
          {
            "result": {
              "status": "skipped"
            },
            "line": 10,
            "name": "I naviagate to Registry for Wedding",
            "match": {
              "location": "RegistryPageStepDefinitions.i_naviagate_to_Registry_for_Wedding()"
            },
            "keyword": "And "
          },
          {
            "result": {
              "status": "skipped"
            },
            "line": 11,
            "name": "I click on Create Your Registry  button",
            "match": {
              "location": "RegistryPageStepDefinitions.i_click_on_Create_Your_Registry_button()"
            },
            "keyword": "When "
          },
          {
            "result": {
              "status": "skipped"
            },
            "line": 12,
            "name": "I Sign In with my credentails",
            "match": {
              "location": "RegistryPageStepDefinitions.i_Sign_In_with_my_credentails()"
            },
            "keyword": "And "
          },
          {
            "result": {
              "status": "skipped"
            },
            "line": 13,
            "name": "I can build the registry of my dreams",
            "match": {
              "location": "RegistryPageStepDefinitions.i_can_build_the_registry_of_my_dreams()"
            },
            "keyword": "Then "
          },
          {
            "result": {
              "status": "skipped"
            },
            "line": 14,
            "name": "I can see a greeting header by our name",
            "match": {
              "location": "RegistryPageStepDefinitions.i_can_see_a_greeting_header_by_our_name()"
            },
            "keyword": "And "
          }
        ]
      }
    ],
    "name": "As an User",
    "description": "I want to create weddding Registry with my credentails to Amazon application \nIn order to get access of the Registry wedding application features",
    "id": "as-an-user",
    "keyword": "Feature",
    "uri": "registryPage.feature",
    "tags": [
      {
        "line": 1,
        "name": "@WeddingRegistry"
      }
    ]
  },
  {
    "line": 2,
    "elements": [
      {
        "comments": [
          {
            "line": 7,
            "value": "#This is imperative BDD, line by line description"
          }
        ],
        "line": 9,
        "name": "User navigates to Application URL",
        "description": "",
        "type": "background",
        "keyword": "Background",
        "steps": [
          {
            "result": {
              "status": "skipped"
            },
            "line": 10,
            "name": "I am on the Amazon page URL \"https://www.amazon.com\"",
            "match": {
              "arguments": [
                {
                  "val": "https://www.amazon.com",
                  "offset": 29
                }
              ],
              "location": "SigninPageStepDefinitions.i_am_on_the_Amazon_page_URL(String)"
            },
            "keyword": "Given "
          },
          {
            "result": {
              "status": "skipped"
            },
            "line": 11,
            "name": "I should see the title and logo of the Amazon application",
            "match": {
              "location": "SigninPageStepDefinitions.i_should_see_the_title_and_logo_of_the_Amazon_application()"
            },
            "keyword": "Then "
          }
        ]
      },
      {
        "before": [
          {
            "result": {
              "duration": 232506,
              "error_message": "java.lang.NullPointerException\n\tat java.util.Objects.requireNonNull(Objects.java:203)\n\tat org.openqa.selenium.interactions.Actions.\u003cinit\u003e(Actions.java:65)\n\tat com.amazonbdd.test.qa.testBase.TestBase.\u003cinit\u003e(TestBase.java:14)\n\tat com.amazonbdd.test.qa.stepdefinitions.ServiceHooks.initializeTest(ServiceHooks.java:24)\n\tat sun.reflect.NativeMethodAccessorImpl.invoke0(Native Method)\n\tat sun.reflect.NativeMethodAccessorImpl.invoke(NativeMethodAccessorImpl.java:62)\n\tat sun.reflect.DelegatingMethodAccessorImpl.invoke(DelegatingMethodAccessorImpl.java:43)\n\tat java.lang.reflect.Method.invoke(Method.java:498)\n\tat cucumber.runtime.Utils$1.call(Utils.java:40)\n\tat cucumber.runtime.Timeout.timeout(Timeout.java:16)\n\tat cucumber.runtime.Utils.invoke(Utils.java:34)\n\tat cucumber.runtime.java.JavaHookDefinition.execute(JavaHookDefinition.java:60)\n\tat cucumber.runtime.Runtime.runHookIfTagsMatch(Runtime.java:224)\n\tat cucumber.runtime.Runtime.runHooks(Runtime.java:212)\n\tat cucumber.runtime.Runtime.runBeforeHooks(Runtime.java:202)\n\tat cucumber.runtime.model.CucumberScenario.run(CucumberScenario.java:40)\n\tat cucumber.runtime.model.CucumberFeature.run(CucumberFeature.java:165)\n\tat cucumber.api.testng.TestNGCucumberRunner.runCucumber(TestNGCucumberRunner.java:63)\n\tat com.amazonbdd.test.qa.testRunner.TestRunner.feature(TestRunner.java:28)\n\tat sun.reflect.NativeMethodAccessorImpl.invoke0(Native Method)\n\tat sun.reflect.NativeMethodAccessorImpl.invoke(NativeMethodAccessorImpl.java:62)\n\tat sun.reflect.DelegatingMethodAccessorImpl.invoke(DelegatingMethodAccessorImpl.java:43)\n\tat java.lang.reflect.Method.invoke(Method.java:498)\n\tat org.testng.internal.MethodInvocationHelper.invokeMethod(MethodInvocationHelper.java:86)\n\tat org.testng.internal.Invoker.invokeMethod(Invoker.java:643)\n\tat org.testng.internal.Invoker.invokeTestMethod(Invoker.java:820)\n\tat org.testng.internal.Invoker.invokeTestMethods(Invoker.java:1128)\n\tat org.testng.internal.TestMethodWorker.invokeTestMethods(TestMethodWorker.java:129)\n\tat org.testng.internal.TestMethodWorker.run(TestMethodWorker.java:112)\n\tat org.testng.TestRunner.privateRun(TestRunner.java:782)\n\tat org.testng.TestRunner.run(TestRunner.java:632)\n\tat org.testng.SuiteRunner.runTest(SuiteRunner.java:366)\n\tat org.testng.SuiteRunner.runSequentially(SuiteRunner.java:361)\n\tat org.testng.SuiteRunner.privateRun(SuiteRunner.java:319)\n\tat org.testng.SuiteRunner.run(SuiteRunner.java:268)\n\tat org.testng.SuiteRunnerWorker.runSuite(SuiteRunnerWorker.java:52)\n\tat org.testng.SuiteRunnerWorker.run(SuiteRunnerWorker.java:86)\n\tat org.testng.TestNG.runSuitesSequentially(TestNG.java:1244)\n\tat org.testng.TestNG.runSuitesLocally(TestNG.java:1169)\n\tat org.testng.TestNG.run(TestNG.java:1064)\n\tat org.apache.maven.surefire.testng.TestNGExecutor.run(TestNGExecutor.java:283)\n\tat org.apache.maven.surefire.testng.TestNGXmlTestSuite.execute(TestNGXmlTestSuite.java:75)\n\tat org.apache.maven.surefire.testng.TestNGProvider.invoke(TestNGProvider.java:120)\n\tat org.apache.maven.surefire.booter.ForkedBooter.invokeProviderInSameClassLoader(ForkedBooter.java:384)\n\tat org.apache.maven.surefire.booter.ForkedBooter.runSuitesInProcess(ForkedBooter.java:345)\n\tat org.apache.maven.surefire.booter.ForkedBooter.execute(ForkedBooter.java:126)\n\tat org.apache.maven.surefire.booter.ForkedBooter.main(ForkedBooter.java:418)\n",
              "status": "failed"
            },
            "match": {
              "location": "ServiceHooks.initializeTest()"
            }
          }
        ],
        "line": 14,
        "name": "Sign in with valid credential",
        "description": "",
        "id": "sign-in;sign-in-with-valid-credential",
        "after": [
          {
            "result": {
              "duration": 1042920,
              "error_message": "java.lang.NullPointerException\n\tat com.amazonbdd.test.qa.stepdefinitions.ServiceHooks.endTest(ServiceHooks.java:34)\n\tat sun.reflect.NativeMethodAccessorImpl.invoke0(Native Method)\n\tat sun.reflect.NativeMethodAccessorImpl.invoke(NativeMethodAccessorImpl.java:62)\n\tat sun.reflect.DelegatingMethodAccessorImpl.invoke(DelegatingMethodAccessorImpl.java:43)\n\tat java.lang.reflect.Method.invoke(Method.java:498)\n\tat cucumber.runtime.Utils$1.call(Utils.java:40)\n\tat cucumber.runtime.Timeout.timeout(Timeout.java:16)\n\tat cucumber.runtime.Utils.invoke(Utils.java:34)\n\tat cucumber.runtime.java.JavaHookDefinition.execute(JavaHookDefinition.java:60)\n\tat cucumber.runtime.Runtime.runHookIfTagsMatch(Runtime.java:224)\n\tat cucumber.runtime.Runtime.runHooks(Runtime.java:212)\n\tat cucumber.runtime.Runtime.runAfterHooks(Runtime.java:206)\n\tat cucumber.runtime.model.CucumberScenario.run(CucumberScenario.java:46)\n\tat cucumber.runtime.model.CucumberFeature.run(CucumberFeature.java:165)\n\tat cucumber.api.testng.TestNGCucumberRunner.runCucumber(TestNGCucumberRunner.java:63)\n\tat com.amazonbdd.test.qa.testRunner.TestRunner.feature(TestRunner.java:28)\n\tat sun.reflect.NativeMethodAccessorImpl.invoke0(Native Method)\n\tat sun.reflect.NativeMethodAccessorImpl.invoke(NativeMethodAccessorImpl.java:62)\n\tat sun.reflect.DelegatingMethodAccessorImpl.invoke(DelegatingMethodAccessorImpl.java:43)\n\tat java.lang.reflect.Method.invoke(Method.java:498)\n\tat org.testng.internal.MethodInvocationHelper.invokeMethod(MethodInvocationHelper.java:86)\n\tat org.testng.internal.Invoker.invokeMethod(Invoker.java:643)\n\tat org.testng.internal.Invoker.invokeTestMethod(Invoker.java:820)\n\tat org.testng.internal.Invoker.invokeTestMethods(Invoker.java:1128)\n\tat org.testng.internal.TestMethodWorker.invokeTestMethods(TestMethodWorker.java:129)\n\tat org.testng.internal.TestMethodWorker.run(TestMethodWorker.java:112)\n\tat org.testng.TestRunner.privateRun(TestRunner.java:782)\n\tat org.testng.TestRunner.run(TestRunner.java:632)\n\tat org.testng.SuiteRunner.runTest(SuiteRunner.java:366)\n\tat org.testng.SuiteRunner.runSequentially(SuiteRunner.java:361)\n\tat org.testng.SuiteRunner.privateRun(SuiteRunner.java:319)\n\tat org.testng.SuiteRunner.run(SuiteRunner.java:268)\n\tat org.testng.SuiteRunnerWorker.runSuite(SuiteRunnerWorker.java:52)\n\tat org.testng.SuiteRunnerWorker.run(SuiteRunnerWorker.java:86)\n\tat org.testng.TestNG.runSuitesSequentially(TestNG.java:1244)\n\tat org.testng.TestNG.runSuitesLocally(TestNG.java:1169)\n\tat org.testng.TestNG.run(TestNG.java:1064)\n\tat org.apache.maven.surefire.testng.TestNGExecutor.run(TestNGExecutor.java:283)\n\tat org.apache.maven.surefire.testng.TestNGXmlTestSuite.execute(TestNGXmlTestSuite.java:75)\n\tat org.apache.maven.surefire.testng.TestNGProvider.invoke(TestNGProvider.java:120)\n\tat org.apache.maven.surefire.booter.ForkedBooter.invokeProviderInSameClassLoader(ForkedBooter.java:384)\n\tat org.apache.maven.surefire.booter.ForkedBooter.runSuitesInProcess(ForkedBooter.java:345)\n\tat org.apache.maven.surefire.booter.ForkedBooter.execute(ForkedBooter.java:126)\n\tat org.apache.maven.surefire.booter.ForkedBooter.main(ForkedBooter.java:418)\n",
              "status": "failed"
            },
            "match": {
              "location": "ServiceHooks.endTest(Scenario)"
            }
          }
        ],
        "type": "scenario",
        "keyword": "Scenario",
        "steps": [
          {
            "result": {
              "status": "skipped"
            },
            "line": 15,
            "name": "I hover over on sign in area",
            "match": {
              "location": "SigninPageStepDefinitions.i_hover_over_on_sign_in_area()"
            },
            "keyword": "When "
          },
          {
            "result": {
              "status": "skipped"
            },
            "line": 16,
            "name": "I click on signin button",
            "match": {
              "location": "SigninPageStepDefinitions.i_click_on_signin_button()"
            },
            "keyword": "And "
          },
          {
            "result": {
              "status": "skipped"
            },
            "line": 17,
            "name": "I enter email in input field as \"tofael483@gmail.com\"",
            "match": {
              "arguments": [
                {
                  "val": "tofael483@gmail.com",
                  "offset": 33
                }
              ],
              "location": "SigninPageStepDefinitions.i_enter_email_in_input_field_as(String)"
            },
            "keyword": "And "
          },
          {
            "result": {
              "status": "skipped"
            },
            "line": 18,
            "name": "I click in continue button",
            "match": {
              "location": "SigninPageStepDefinitions.i_click_in_continue_button()"
            },
            "keyword": "And "
          },
          {
            "result": {
              "status": "skipped"
            },
            "line": 19,
            "name": "I enter password in input field as \"Nabeeha19\"",
            "match": {
              "arguments": [
                {
                  "val": "Nabeeha19",
                  "offset": 36
                }
              ],
              "location": "SigninPageStepDefinitions.i_enter_password_in_input_field_as(String)"
            },
            "keyword": "And "
          },
          {
            "result": {
              "status": "skipped"
            },
            "line": 20,
            "name": "I click in SignIn button",
            "match": {
              "location": "SigninPageStepDefinitions.i_click_in_SignIn_button()"
            },
            "keyword": "And "
          },
          {
            "result": {
              "status": "skipped"
            },
            "line": 21,
            "name": "I sould see the title of the SignIn page",
            "match": {
              "location": "SigninPageStepDefinitions.i_sould_see_the_title_of_the_SignIn_page()"
            },
            "keyword": "Then "
          }
        ]
      }
    ],
    "name": "Sign In",
    "description": "As an User\nI want to Sign In with my credentails to Amazon application \nIn order to get access of the application features",
    "id": "sign-in",
    "keyword": "Feature",
    "uri": "signinPage.feature",
    "tags": [
      {
        "line": 1,
        "name": "@SignIn"
      }
    ]
  }
]